Metadata-Version: 1.1
Name: coverage-filter
Version: 0.0.0
Summary: Coverage filter
Home-page: https://github.com/ondergetekende/coverage_filter
Author: Koert van der Veer
Author-email: py@ondergetekende.nl
License: MIT
Keywords: unit test coverage
Platform: UNKNOWN
Classifier: Development Status :: 2 - Pre-Alpha
Classifier: Intended Audience :: Developers
Classifier: Topic :: Software Development :: Build Tools
Classifier: License :: OSI Approved :: MIT License
Classifier: Programming Language :: Python :: 3
Classifier: Programming Language :: Python :: 3.3
Classifier: Programming Language :: Python :: 3.4
Classifier: Programming Language :: Python :: 3.5
